smtp_credentials/__init__.py
smtp_credentials/py.typed
smtp_credentials/_jsii/__init__.py
smtp_credentials/_jsii/smtp-credentials-cdk-construct@2.0.0.jsii.tgz
smtp_credentials_cdk_construct-2.0.0.dist-info/LICENSE
smtp_credentials_cdk_construct-2.0.0.dist-info/METADATA
smtp_credentials_cdk_construct-2.0.0.dist-info/WHEEL
smtp_credentials_cdk_construct-2.0.0.dist-info/top_level.txt
smtp_credentials_cdk_construct-2.0.0.dist-info/RECORD
