Metadata-Version: 2.1
Name: smtp-credentials-cdk-construct
Version: 2.0.0
Summary: A CDK construct that creates SMTP credentials permitting emails to be sent via SES.
Home-page: https://github.com/charlesdotfish/smtp-credentials-cdk-construct
Author: Charles Salmon<me@charles.fish>
License: MIT
Project-URL: Source, https://github.com/charlesdotfish/smtp-credentials-cdk-construct
Platform: UNKNOWN
Classifier: Intended Audience :: Developers
Classifier: Operating System :: OS Independent
Classifier: Programming Language :: JavaScript
Classifier: Programming Language :: Python :: 3 :: Only
Classifier: Programming Language :: Python :: 3.7
Classifier: Programming Language :: Python :: 3.8
Classifier: Programming Language :: Python :: 3.9
Classifier: Programming Language :: Python :: 3.10
Classifier: Typing :: Typed
Classifier: Development Status :: 5 - Production/Stable
Classifier: License :: OSI Approved
Requires-Python: ~=3.7
License-File: LICENSE
Requires-Dist: aws-cdk-lib (<3.0.0,>=2.24.1)
Requires-Dist: constructs (<11.0.0,>=10.0.5)
Requires-Dist: jsii (<2.0.0,>=1.59.0)
Requires-Dist: publication (>=0.0.3)
